mailclerk/__init__.py
mailclerk/api_client.py
mailclerk/errors.py
mailclerk/outbox.py
mailclerk-1.2.0.dist-info/LICENSE.md
mailclerk-1.2.0.dist-info/METADATA
mailclerk-1.2.0.dist-info/WHEEL
mailclerk-1.2.0.dist-info/top_level.txt
mailclerk-1.2.0.dist-info/RECORD
