Metadata-Version: 2.1
Name: mailclerk
Version: 1.2.0
Summary: Send mail with mailclerk.app
Home-page: https://github.com/mailclerk/mailclerk-python
Author: Greg Sherrid
Author-email: developers@mailclerk.app
License: UNKNOWN
Platform: UNKNOWN
Classifier: Intended Audience :: Developers
Classifier: Programming Language :: Python :: 2.7
Classifier: Programming Language :: Python :: 3.5
Requires-Dist: requests[security] (>=2.20) ; python_version < "3.0"
Requires-Dist: requests (>=2.20) ; python_version >= "3.0"
Provides-Extra: test
Requires-Dist: python-dotenv ; extra == 'test'
